rtl/control.v
module CONTROL_UNIT (
    input clk,
    input reset,

    input [31:0] pc,
    input [31:0] mem_read,
    input [31:0] rs1_in,
    input [31:0] rs2_in,
    input [63:0] rd_output,
    input [6:0] opcode,
    input [2:0] funct3,
    input [6:0] funct7,
    input [31:0] imm_ext,

    output reg [31:0] alu_in1,
    output reg [31:0] alu_in2,
    output reg [31:0] out, 
    output reg [7:0] aluop,
    output reg wr_en_rf,
    output reg wr_en_mem,
    output reg [31:0] mem_data_wr,
    output reg [31:0] mem_addr,
    output reg [3:0] mem_mask,
    output reg [31:0] jump_pc,
    output reg is_jump
);

    wire [1:0] byte_sel;
    assign byte_sel = rd_output[1:0]; 

    always @(*) begin
        
        alu_in1     = rs1_in;
        alu_in2     = rs2_in;
        out         = rd_output; 
        aluop       = 8'd0;
        wr_en_rf    = 0;
        wr_en_mem   = 0;
        mem_data_wr = rs2_in;
        mem_addr    = rd_output[31:0];
        mem_mask    = 4'b0000;
        jump_pc     = pc + imm_ext;
        is_jump     = 0;

        case(opcode)

        7'b0110011,7'b0010011 : begin //R-TYPE / I-TYPE
            wr_en_rf = 1;

            if ((opcode == 7'b0110011) && (funct7 == 7'b0000001)) begin //M-TYPE
                case(funct3)

                3'b000 : begin //MUL
                    alu_in1 = rs1_in;
                    alu_in2 = rs2_in;
                    out = rd_output[31:0];
                    aluop = 8'd3;
                end
 
                3'b001 : begin //MULH
                    alu_in1 = rs1_in;
                    alu_in2 = rs2_in;
                    out = rd_output[63:32];
                    aluop = 8'd3;
                end

                3'b101 : begin //DIV
                    alu_in1 = rs1_in;
                    alu_in2 = rs2_in;
                    out = rd_output;
                    aluop = 8'd4;
                end

                3'b111 : begin //REM
                    alu_in1 = rs1_in;
                    alu_in2 = rs2_in;
                    out = rd_output;
                    aluop = 8'd5;
                end

                endcase
            end

            else begin
                case(funct3)
                
                3'b000 : begin //ADD/SUB
                    alu_in1 = rs1_in;
                    alu_in2 = (opcode == 7'b0010011) ? imm_ext : rs2_in; //IMM FOR I-TYPE : RS2 FOR R-TYPE
                    out = rd_output;
                    aluop = ((opcode == 7'b0110011) && funct7[5]) ? 8'd2 : 8'd1; //SUB:ADD
                end

                3'b001 : begin //SLL
                    alu_in1 = rs1_in;
                    alu_in2 = (opcode == 7'b0010011) ? imm_ext : rs2_in;
                    out = rd_output;
                    aluop = 8'd9;
                end

                3'b100 : begin //XOR
                    alu_in1 = rs1_in;
                    alu_in2 = rs2_in;
                    out = rd_output;
                    aluop = 8'd8;
                end

                3'b101 : begin //SRL/SRA
                    alu_in1 = rs1_in;
                    alu_in2 = (opcode == 7'b0010011) ? imm_ext : rs2_in;
                    out = rd_output;
                    aluop = (funct7[5]) ? 8'd11 : 8'd10; //SRA:SRL
                end

                3'b110 : begin //OR
                    alu_in1 = rs1_in;
                    alu_in2 = (opcode == 7'b0010011) ? imm_ext : rs2_in;
                    out = rd_output;
                    aluop = 8'd7;
                end

                3'b111 : begin //AND
                    alu_in1 = rs1_in;
                    alu_in2 = (opcode == 7'b0010011) ? imm_ext : rs2_in;
                    out = rd_output;
                    aluop = 8'd6;
                end

                endcase
            end
        end
        
        7'b0110111,7'b0010111 : begin //U-TYPE 
            wr_en_rf = 1;

            aluop = 0;
            out = (opcode == 7'b0110111) ? imm_ext : pc + imm_ext;
        end

        7'b1100011 : begin //B-TYPE
            
            case(funct3)
            
            3'b000 : begin //BEQ
                alu_in1 = rs1_in;
                alu_in2 = rs2_in;
                aluop = 8'd2;
                jump_pc = pc + imm_ext;
                is_jump = (rs1_in == rs2_in);           
            end

            3'b001 : begin //BNE
                alu_in1 = rs1_in;
                alu_in2 = rs2_in;
                aluop = 8'd2;
                jump_pc = pc + imm_ext;
                is_jump = (rs1_in != rs2_in);           
            end

            endcase
        end

        7'b1101111 : begin //J-TYPE
            wr_en_rf = 1; //JAL
            is_jump = 1;
            jump_pc = pc + imm_ext;
            out = pc + 4;
        end

        7'b0100011 : begin //S-TYPE
            wr_en_mem = 1;
            
            alu_in1 = rs1_in;
            alu_in2 = imm_ext;
            aluop = 8'd1;
            mem_data_wr = rs2_in;
            mem_addr = rd_output[31:0];

            case(funct3)

            3'b000 : begin //SB
                case(byte_sel)

                2'b00 : mem_mask = 4'b0001;
                2'b01 : mem_mask = 4'b0010;
                2'b10 : mem_mask = 4'b0100;
                2'b11 : mem_mask = 4'b1000;

                endcase
            end 

            3'b001 : mem_mask = (byte_sel[1]) ? 4'b1100 : 4'b0011; //SH

            3'b010 : mem_mask = 4'b1111; ///SW

            endcase
        end

        7'b0000011 : begin //LOAD
            wr_en_rf = 1;
            alu_in1 = rs1_in;
            alu_in2 = imm_ext;
            aluop = 8'd1;
            mem_addr = rd_output[31:0];
            mem_mask = 4'b1111;
            out = mem_read;
        end

        default begin
            wr_en_rf = 0;
            wr_en_mem = 0;
            is_jump =  0;
            aluop = 8'd0;
        end

        endcase

    end

    
endmodule

rtl/alu.v
module ALU (
    input [7:0] alucode,
    input [31:0] rs1,
    input [31:0] rs2,
    output reg [63:0] rd
);


    always @(*) begin
    
        case(alucode)

        8'd1 : rd = rs1 + rs2 ; //ADD
        8'd2 : rd = rs1 - rs2 ; //SUB
        8'd3 : rd = rs1 * rs2 ; //MUL
        8'd4 : rd = $signed(rs1) / $signed(rs2) ; //DIV
        8'd5 : rd = $signed(rs1) % $signed(rs2); //REM
        8'd6 : rd = rs1 & rs2 ; //AND
        8'd7 : rd = rs1 | rs2 ; //OR
        8'd8 : rd = rs1 ^ rs2 ; //XOR
        8'd9 : rd = rs1 << rs2[4:0]; //SLL
        8'd10 : rd = rs1 >> rs2[4:0]; //SRL
        8'd11 : rd = $signed(rs1) >>> rs2[4:0]; //SRA
        default : rd = 0 ; //DEFAULT

        endcase

    end

   
endmodule

rtl/decoder.v
module DECODER (
    input [31:0] instr,
    output [4:0] rs1_addr,
    output [4:0] rs2_addr,
    output [4:0] rd_addr,
    output [6:0] opcode,
    output [2:0] funct3,
    output [6:0] funct7,
    output reg [31:0] imm_ext
);

    assign opcode = instr[6:0];
    assign rd_addr = instr[11:7];
    assign funct3 = instr[14:12];
    assign rs1_addr = instr[19:15];
    assign rs2_addr = instr[24:20];
    assign funct7 = instr[31:25];

    //Immediate Value Extension

    always @(*) begin
        
        if ((opcode == 7'b0010011) || (opcode == 7'b0000011)) begin 
            imm_ext = {{20{instr[31]}}, instr[31:20]} ; end //I-Type Instruction
        else if ((opcode == 7'b0110111) || (opcode == 7'b0010111)) begin 
             imm_ext = {instr[31:12], 12'b0} ; end //U-Type Instruction
        else if ((opcode == 7'b1100011)) begin 
             imm_ext = {{19{instr[31]}}, instr[31], instr[7], instr[30:25], instr[11:8], 1'b0} ; end //B-Type Instruction 
        else if ((opcode == 7'b1101111)) begin 
             imm_ext = {{11{instr[31]}}, instr[31], instr[19:12], instr[20], instr[30:21], 1'b0} ; end //J-Type Instruction
        else if ((opcode == 7'b0100011)) begin 
            imm_ext = {{20{instr[31]}}, instr[31:25], instr[11:7]} ; end //S-Type Instruction
        else begin
            imm_ext = 32'b0; end

    end
  
endmodule

rtl/datamem.v
module DATAMEM (
    input clk,
    input [31:0] addr,
    input [31:0] mem_data_wr,
    input wr_en_mem,
    input [3:0] mem_mask,
    output reg [31:0] mem_read_data
);

    reg [31:0] datamem [0:2047];
    wire [10:0] word_addr = addr[12:2];

    initial begin
    $readmemh("./sim/data_mem.hex", datamem);
    end

    always @(*) begin

        if(wr_en_mem) begin
            mem_read_data <= 32'b0;
        end
        else begin

            case(mem_mask)

            4'b0001 : mem_read_data = {{24{datamem[word_addr][7]}}, datamem[word_addr][7:0] };
            4'b0010 : mem_read_data = {{24{datamem[word_addr][15]}}, datamem[word_addr][15:8] };
            4'b0100 : mem_read_data = {{24{datamem[word_addr][23]}}, datamem[word_addr][23:16] };
            4'b1000 : mem_read_data = {{24{datamem[word_addr][31]}}, datamem[word_addr][31:24] };
            4'b0011 : mem_read_data = {{16{datamem[word_addr][15]}}, datamem[word_addr][15:0] };
            4'b1100 : mem_read_data = {{16{datamem[word_addr][31]}}, datamem[word_addr][31:16] };
            4'b1111 : mem_read_data = datamem[word_addr];
            default : mem_read_data = datamem[word_addr];

            endcase
        end
    end

    always @(posedge clk) begin
        
        if(wr_en_mem) begin

            if(mem_mask[0]) datamem[word_addr][7:0] <= mem_data_wr[7:0];
            if(mem_mask[1]) datamem[word_addr][15:8] <= mem_data_wr[15:8];
            if(mem_mask[2]) datamem[word_addr][23:16] <= mem_data_wr[23:16];
            if(mem_mask[3]) datamem[word_addr][31:24] <= mem_data_wr[31:24];

        end

    end

endmodule

rtl/instrmem.v
module INSTRMEM (
    input [31:0] instr_addr,
    output [31:0] instr
);

reg [31:0] instrmem [0:511];

initial begin
$readmemh("C:\Users\Mayuresh\OneDrive\Desktop\Sanganac\Sanganac\sim\instr_program.hex", instrmem)
end

assign instr = instrmem[instr_addr >> 2];
    
endmodule

rtl/regfile.v
module REGFILE (
    input clk,
    input wr_en,
    input [4:0] rs1_addr,
    input [4:0] rs2_addr,
    input [4:0] rd_addr,
    input [31:0] rd,
    output reg [31:0] rs1,
    output reg [31:0] rs2
);


    reg [31:0] regfile [31:0];

    initial begin
        
        regfile[0] <= 0;
        regfile[1] <= 0;
        regfile[2] <= 0;
        regfile[3] <= 0;
        regfile[4] <= 0;
        regfile[5] <= 0;
        regfile[6] <= 0;
        regfile[7] <= 0;
        regfile[8] <= 0;
        regfile[9] <= 0;
        regfile[10] <= 0;
        regfile[11] <= 0;
        regfile[12] <= 0;
        regfile[13] <= 0;
        regfile[14] <= 0;
        regfile[15] <= 0;
        regfile[16] <= 0;
        regfile[17] <= 0;
        regfile[18] <= 0;
        regfile[19] <= 0;
        regfile[20] <= 0;
        regfile[21] <= 0;
        regfile[22] <= 0;
        regfile[23] <= 0;
        regfile[24] <= 0;
        regfile[25] <= 0;
        regfile[26] <= 0;
        regfile[27] <= 0;
        regfile[28] <= 0;
        regfile[29] <= 0;
        regfile[30] <= 0;
        regfile[31] <= 0;

    end

    always @(*) begin
        rs1 = regfile[rs1_addr];
        rs2 = regfile[rs2_addr];   
    end

    always @(posedge clk) begin
        regfile[0] <= 0;

        if (wr_en && rd_addr != 5'd0) begin
            regfile[rd_addr] <= rd;
        end
    end


endmodule

rtl/pc.v
module PC (
    input clk,
    input reset,
    input [31:0] jump_pc,
    input is_jump,
    output [31:0] pc_next
);

    reg [31:0] pc;

    always @(posedge clk or posedge reset) begin
        
        if (reset) begin
            pc <= 32'b0;
        end
        else if (is_jump) begin
            pc <= jump_pc;
        end
        else begin
            pc <= pc + 32'd4;
        end
    
    end

    assign pc_next = pc;
    
endmodule

rtl/riscv_core.v
module RISCV_CORE (
    input clk,
    input reset
);

    wire [31:0] pc_current, jump_pc, instr, imm_ext;
    wire [4:0] rs1_addr, rs2_addr, rd_addr;
    wire [31:0] rs1, rs2, rd;
    wire [63:0] alu_output;
    wire [31:0] alu_in1, alu_in2;
    wire [31:0] mem_addr, mem_read_data, mem_data_wr;
    wire [6:0] opcode, funct7;
    wire [2:0] funct3;
    wire [7:0] aluop;
    wire [3:0] mem_mask;
    wire wr_en_rf, wr_en_mem, is_jump;

    PC pc (
        .clk(clk),
        .reset(reset),
        .jump_pc(jump_pc),
        .is_jump(is_jump),
        .pc_next(pc_current)
    );

    REGFILE regfile (
        .clk(clk),
        .wr_en(wr_en_rf),
        .rs1_addr(rs1_addr),
        .rs2_addr(rs2_addr),
        .rd_addr(rd_addr),
        .rd(rd),
        .rs1(rs1),
        .rs2(rs2)
    );

    INSTRMEM instrmem (
        .instr_addr(pc_current),
        .instr(instr)
    );

    DATAMEM datamem (
        .clk(clk),
        .addr(mem_addr),
        .mem_data_wr(mem_data_wr),
        .wr_en_mem(wr_en_mem),
        .mem_mask(mem_mask),
        .mem_read_data(mem_read_data)
);  

    DECODER decoder (
        .instr(instr),
        .rs1_addr(rs1_addr),
        .rs2_addr(rs2_addr),
        .rd_addr(rd_addr),
        .opcode(opcode),
        .funct3(funct3),
        .funct7(funct7),
        .imm_ext(imm_ext)
    );

    ALU alu (
        .alucode(aluop),
        .rs1(alu_in1),
        .rs2(alu_in2),
        .rd(alu_output)
    );

    CONTROL_UNIT control_unit (
        .clk(clk),
        .reset(reset),

        .pc(pc_current),
        .mem_read(mem_read_data),
        .rs1_in(rs1),
        .rs2_in(rs2),
        .rd_output(alu_output),
        .opcode(opcode),
        .funct3(funct3),
        .funct7(funct7),
        .imm_ext(imm_ext),

        .alu_in1(alu_in1),
        .alu_in2(alu_in2),
        .out(rd), 
        .aluop(aluop),
        .wr_en_rf(wr_en_rf),
        .wr_en_mem(wr_en_mem),
        .mem_data_wr(mem_data_wr),
        .mem_addr(mem_addr),
        .mem_mask(mem_mask),
        .jump_pc(jump_pc),
        .is_jump(is_jump)
    );
    
endmodule

rtl/top.v
module TOP (
    input clk,
    input reset
);

    RISCV_CORE sanganac (
        .clk(clk),
        .reset(reset)
    );

endmodule

tb/tb.v
`timescale 1ns/1ps

module tb ();
    
    reg clk;
    reg reset;
    integer i;

    TOP uut (
        .clk(clk),
        .reset(reset)
    );

    initial begin
        clk = 0;
        forever #5 clk = ~clk; 
    end

    initial begin
        $dumpfile("tb.vcd");
        $dumpvars(0, tb);
    end

    initial begin
        reset = 1;
        #50 reset = 0;
        
        #500;

        // 00A00093 ADDI x1, x0, 10
        // 01400113 ADDI x2, x0, 20
        // 002081B3 ADD x3, x1, x2
        // 00302023 SW x3, 0(x0)
        // 00002203 LW x4, 0(x0)
        // 0000006F JAL x0, 0 (Infinite Loop)

        $display("Simulation now completed.");

        $display("======================================================");
        $display("REGISTER FILE :"); 
        for (i = 0; i < 32; i = i + 1) begin
            $display("x%0d : %h", i, uut.sanganac.regfile.regfile[i]);
        end
        $display("======================================================");

        $display("");
        $display("======================================================");
        $display("INSTRUCTION MEMORY :");
        for (i = 0; i < 20; i = i + 1) begin
            $display("%h : %h", i*4, uut.sanganac.instrmem.instrmem[i]);
        end
        $display("======================================================");

        $display("");
        $display("======================================================");
        $display("DATA MEMORY :");
        for (i = 0; i < 20; i = i + 1) begin
            $display("%h : %h", i*4, uut.sanganac.datamem.datamem[i]);
        end
        $display("======================================================");

        $display("");

        $finish;

    end

    initial begin
        $monitor("Time : %0t | Reset : %b | PC : %h | Instruction : %h", 
                 $time, reset, uut.sanganac.pc_current, uut.sanganac.instr);
    end

endmodule

tb.vcd
$date
	Wed Jan 21 21:58:19 2026
$end
$version
	Icarus Verilog
$end
$timescale
	1ps
$end
$scope module tb $end
$var reg 1 ! clk $end
$var reg 1 " reset $end
$var integer 32 # i [31:0] $end
$scope module uut $end
$var wire 1 ! clk $end
$var wire 1 " reset $end
$scope module sanganac $end
$var wire 1 ! clk $end
$var wire 1 " reset $end
$var wire 1 $ wr_en_rf $end
$var wire 1 % wr_en_mem $end
$var wire 5 & rs2_addr [4:0] $end
$var wire 32 ' rs2 [31:0] $end
$var wire 5 ( rs1_addr [4:0] $end
$var wire 32 ) rs1 [31:0] $end
$var wire 5 * rd_addr [4:0] $end
$var wire 32 + rd [31:0] $end
$var wire 32 , pc_current [31:0] $end
$var wire 7 - opcode [6:0] $end
$var wire 32 . mem_read_data [31:0] $end
$var wire 4 / mem_mask [3:0] $end
$var wire 32 0 mem_data_wr [31:0] $end
$var wire 32 1 mem_addr [31:0] $end
$var wire 32 2 jump_pc [31:0] $end
$var wire 1 3 is_jump $end
$var wire 32 4 instr [31:0] $end
$var wire 32 5 imm_ext [31:0] $end
$var wire 7 6 funct7 [6:0] $end
$var wire 3 7 funct3 [2:0] $end
$var wire 8 8 aluop [7:0] $end
$var wire 64 9 alu_output [63:0] $end
$var wire 32 : alu_in2 [31:0] $end
$var wire 32 ; alu_in1 [31:0] $end
$scope module alu $end
$var wire 32 < rs2 [31:0] $end
$var wire 32 = rs1 [31:0] $end
$var wire 8 > alucode [7:0] $end
$var reg 64 ? rd [63:0] $end
$upscope $end
$scope module control_unit $end
$var wire 1 ! clk $end
$var wire 64 @ rd_output [63:0] $end
$var wire 1 " reset $end
$var wire 32 A rs2_in [31:0] $end
$var wire 32 B rs1_in [31:0] $end
$var wire 32 C pc [31:0] $end
$var wire 7 D opcode [6:0] $end
$var wire 32 E mem_read [31:0] $end
$var wire 32 F imm_ext [31:0] $end
$var wire 7 G funct7 [6:0] $end
$var wire 3 H funct3 [2:0] $end
$var wire 2 I byte_sel [1:0] $end
$var reg 32 J alu_in1 [31:0] $end
$var reg 32 K alu_in2 [31:0] $end
$var reg 8 L aluop [7:0] $end
$var reg 1 3 is_jump $end
$var reg 32 M jump_pc [31:0] $end
$var reg 32 N mem_addr [31:0] $end
$var reg 32 O mem_data_wr [31:0] $end
$var reg 4 P mem_mask [3:0] $end
$var reg 32 Q out [31:0] $end
$var reg 1 % wr_en_mem $end
$var reg 1 $ wr_en_rf $end
$upscope $end
$scope module datamem $end
$var wire 32 R addr [31:0] $end
$var wire 1 ! clk $end
$var wire 32 S mem_data_wr [31:0] $end
$var wire 4 T mem_mask [3:0] $end
$var wire 1 % wr_en_mem $end
$var wire 11 U word_addr [10:0] $end
$var reg 32 V mem_read_data [31:0] $end
$upscope $end
$scope module decoder $end
$var wire 5 W rs2_addr [4:0] $end
$var wire 5 X rs1_addr [4:0] $end
$var wire 5 Y rd_addr [4:0] $end
$var wire 7 Z opcode [6:0] $end
$var wire 32 [ instr [31:0] $end
$var wire 7 \ funct7 [6:0] $end
$var wire 3 ] funct3 [2:0] $end
$var reg 32 ^ imm_ext [31:0] $end
$upscope $end
$scope module instrmem $end
$var wire 32 _ instr [31:0] $end
$var wire 32 ` instr_addr [31:0] $end
$upscope $end
$scope module pc $end
$var wire 1 ! clk $end
$var wire 1 3 is_jump $end
$var wire 32 a jump_pc [31:0] $end
$var wire 32 b pc_next [31:0] $end
$var wire 1 " reset $end
$var reg 32 c pc [31:0] $end
$upscope $end
$scope module regfile $end
$var wire 1 ! clk $end
$var wire 32 d rd [31:0] $end
$var wire 5 e rd_addr [4:0] $end
$var wire 5 f rs1_addr [4:0] $end
$var wire 5 g rs2_addr [4:0] $end
$var wire 1 $ wr_en $end
$var reg 32 h rs1 [31:0] $end
$var reg 32 i rs2 [31:0] $end
$upscope $end
$upscope $end
$upscope $end
$upscope $end
$enddefinitions $end
#0
$dumpvars
b0 i
b0 h
b1010 g
b0 f
b1 e
b1010 d
b0 c
b0 b
b1010 a
b0 `
b101000000000000010010011 _
b1010 ^
b0 ]
b0 \
b101000000000000010010011 [
b10011 Z
b1 Y
b0 X
b1010 W
b0 V
b10 U
b0 T
b0 S
b1010 R
b1010 Q
b0 P
b0 O
b1010 N
b1010 M
b1 L
b1010 K
b0 J
b10 I
b0 H
b0 G
b1010 F
b0 E
b10011 D
b0 C
b0 B
b0 A
b1010 @
b1010 ?
b1 >
b0 =
b1010 <
b0 ;
b1010 :
b1010 9
b1 8
b0 7
b0 6
b1010 5
b101000000000000010010011 4
03
b1010 2
b1010 1
b0 0
b0 /
b0 .
b10011 -
b0 ,
b1010 +
b1 *
b0 )
b0 (
b0 '
b1010 &
0%
1$
bx #
1"
0!
$end
#5000
1!
#10000
0!
#15000
1!
#20000
0!
#25000
1!
#30000
0!
#35000
1!
#40000
0!
#45000
1!
#50000
0!
0"
#55000
bx .
bx E
bx V
b101 U
b10100 1
b10100 N
b10100 R
b10100 +
b10100 Q
b10100 d
b0 I
b10100 9
b10100 ?
b10100 @
b10100 &
b10100 W
b10100 g
b10 *
b10 Y
b10 e
b10100 5
b10100 F
b10100 ^
b1010000000000000100010011 4
b1010000000000000100010011 [
b1010000000000000100010011 _
b11000 2
b11000 M
b11000 a
1$
b1 8
b1 >
b1 L
b10100 :
b10100 <
b10100 K
b100 ,
b100 C
b100 `
b100 b
b100 c
1!
#60000
0!
#65000
bx .
bx E
bx V
b10 I
b111 U
b11110 1
b11110 N
b11110 R
b10100 0
b10100 O
b10100 S
b11110 +
b11110 Q
b11110 d
b1010 ;
b1010 =
b1010 J
b11110 9
b11110 ?
b11110 @
b10100 '
b10100 A
b10100 i
b1010 )
b1010 B
b1010 h
b10 &
b10 W
b10 g
b1 (
b1 X
b1 f
b11 *
b11 Y
b11 e
b110011 -
b110011 D
b110011 Z
b0 5
b0 F
b0 ^
b1000001000000110110011 4
b1000001000000110110011 [
b1000001000000110110011 _
b1000 2
b1000 M
b1000 a
1$
b1 8
b1 >
b1 L
b10100 :
b10100 <
b10100 K
b1000 ,
b1000 C
b1000 `
b1000 b
b1000 c
1!
#70000
0!
#75000
b0 .
b0 E
b0 V
b0 I
b0 U
b0 1
b0 N
b0 R
b11110 0
b11110 O
b11110 S
b0 +
b0 Q
b0 d
b0 ;
b0 =
b0 J
b0 9
b0 ?
b0 @
b11110 '
b11110 A
b11110 i
b0 )
b0 B
b0 h
b1111 /
b1111 P
b1111 T
b0 :
b0 <
b0 K
1%
b11 &
b11 W
b11 g
b0 (
b0 X
b0 f
b10 7
b10 H
b10 ]
b0 *
b0 Y
b0 e
b100011 -
b100011 D
b100011 Z
b1100000010000000100011 4
b1100000010000000100011 [
b1100000010000000100011 _
b1100 2
b1100 M
b1100 a
0$
b1 8
b1 >
b1 L
b1100 ,
b1100 C
b1100 `
b1100 b
b1100 c
1!
#80000
0!
#85000
b0 U
b0 1
b0 N
b0 R
b0 0
b0 O
b0 S
b11110 +
b11110 Q
b11110 d
b11110 .
b11110 E
b11110 V
b0 9
b0 ?
b0 @
b0 '
b0 A
b0 i
1$
b0 &
b0 W
b0 g
b100 *
b100 Y
b100 e
b11 -
b11 D
b11 Z
b0 5
b0 F
b0 ^
b10001000000011 4
b10001000000011 [
b10001000000011 _
b10000 2
b10000 M
b10000 a
b1111 /
b1111 P
b1111 T
0%
b1 8
b1 >
b1 L
b0 :
b0 <
b0 K
b10000 ,
b10000 C
b10000 `
b10000 b
b10000 c
1!
#90000
0!
#95000
13
b0 7
b0 H
b0 ]
b0 *
b0 Y
b0 e
b1101111 -
b1101111 D
b1101111 Z
b1101111 4
b1101111 [
b1101111 _
b10100 2
b10100 M
b10100 a
b0 /
b0 P
b0 T
1$
b0 8
b0 >
b0 L
b11000 +
b11000 Q
b11000 d
b10100 ,
b10100 C
b10100 `
b10100 b
b10100 c
1!
#100000
0!
#105000
1!
#110000
0!
#115000
1!
#120000
0!
#125000
1!
#130000
0!
#135000
1!
#140000
0!
#145000
1!
#150000
0!
#155000
1!
#160000
0!
#165000
1!
#170000
0!
#175000
1!
#180000
0!
#185000
1!
#190000
0!
#195000
1!
#200000
0!
#205000
1!
#210000
0!
#215000
1!
#220000
0!
#225000
1!
#230000
0!
#235000
1!
#240000
0!
#245000
1!
#250000
0!
#255000
1!
#260000
0!
#265000
1!
#270000
0!
#275000
1!
#280000
0!
#285000
1!
#290000
0!
#295000
1!
#300000
0!
#305000
1!
#310000
0!
#315000
1!
#320000
0!
#325000
1!
#330000
0!
#335000
1!
#340000
0!
#345000
1!
#350000
0!
#355000
1!
#360000
0!
#365000
1!
#370000
0!
#375000
1!
#380000
0!
#385000
1!
#390000
0!
#395000
1!
#400000
0!
#405000
1!
#410000
0!
#415000
1!
#420000
0!
#425000
1!
#430000
0!
#435000
1!
#440000
0!
#445000
1!
#450000
0!
#455000
1!
#460000
0!
#465000
1!
#470000
0!
#475000
1!
#480000
0!
#485000
1!
#490000
0!
#495000
1!
#500000
0!
#505000
1!
#510000
0!
#515000
1!
#520000
0!
#525000
1!
#530000
0!
#535000
1!
#540000
0!
#545000
1!
#550000
0!
b10100 #
