rtl/control.v
module CONTROL_UNIT (
    input clk,
    input reset,

    input [31:0] pc,
    input [31:0] mem_read,
    input [31:0] rs1_in,
    input [31:0] rs2_in,
    input [63:0] rd_output,
    input [6:0] opcode,
    input [2:0] funct3,
    input [6:0] funct7,
    input [31:0] imm_ext,

    output reg [31:0] alu_in1,
    output reg [31:0] alu_in2,
    output reg [31:0] out, 
    output reg [7:0] aluop,
    output reg wr_en_rf,
    output reg wr_en_mem,
    output reg read_en_mem,
    output reg [31:0] mem_data_wr,
    output reg [31:0] mem_addr,
    output reg [3:0] mem_mask,
    output reg [31:0] jump_pc,
    output reg is_jump
);

    wire [1:0] byte_sel;
    assign byte_sel = rd_output[1:0]; 

    always @(*) begin
        
        alu_in1     = rs1_in;
        alu_in2     = rs2_in;
        out         = 32'b0; 
        aluop       = 8'd0;
        wr_en_rf    = 0;
        wr_en_mem   = 0;
        read_en_mem = 0;
        mem_data_wr = rs2_in;
        mem_addr    = rd_output[31:0];
        mem_mask    = 4'b0000;
        jump_pc     = pc + imm_ext;
        is_jump     = 0;

        case(opcode)

        7'b0110011,7'b0010011 : begin //R-TYPE / I-TYPE
            wr_en_rf = 1;

            if ((opcode == 7'b0110011) && (funct7 == 7'b0000001)) begin //M-TYPE
                case(funct3)

                3'b000 : begin //MUL
                    alu_in1 = rs1_in;
                    alu_in2 = rs2_in;
                    aluop = 8'd3;
                    out = rd_output[31:0];
                end
 
                3'b001 : begin //MULH
                    alu_in1 = rs1_in;
                    alu_in2 = rs2_in;
                    aluop = 8'd3;
                    out = rd_output[63:32];
                end

                3'b101 : begin //DIV
                    alu_in1 = rs1_in;
                    alu_in2 = rs2_in;
                    aluop = 8'd4;
                    out = rd_output;
                end

                3'b111 : begin //REM
                    alu_in1 = rs1_in;
                    alu_in2 = rs2_in;
                    aluop = 8'd5;
                    out = rd_output;
                end

                endcase
            end

            else begin
                case(funct3)
                
                3'b000 : begin //ADD/SUB
                    alu_in1 = rs1_in;
                    alu_in2 = (opcode == 7'b0010011) ? imm_ext : rs2_in; //IMM FOR I-TYPE : RS2 FOR R-TYPE
                    aluop = ((opcode == 7'b0110011) && funct7[5]) ? 8'd2 : 8'd1; //SUB:ADD
                    out = rd_output;
                end

                3'b001 : begin //SLL
                    alu_in1 = rs1_in;
                    alu_in2 = (opcode == 7'b0010011) ? imm_ext : rs2_in;
                    aluop = 8'd9;
                    out = rd_output;
                end

                3'b100 : begin //XOR
                    alu_in1 = rs1_in;
                    alu_in2 = rs2_in;
                    aluop = 8'd8;
                    out = rd_output;
                end

                3'b101 : begin //SRL/SRA
                    alu_in1 = rs1_in;
                    alu_in2 = (opcode == 7'b0010011) ? imm_ext : rs2_in;
                    aluop = (funct7[5]) ? 8'd11 : 8'd10; //SRA:SRL
                    out = rd_output;
                end

                3'b110 : begin //OR
                    alu_in1 = rs1_in;
                    alu_in2 = (opcode == 7'b0010011) ? imm_ext : rs2_in;
                    aluop = 8'd7;
                    out = rd_output;
                end

                3'b111 : begin //AND
                    alu_in1 = rs1_in;
                    alu_in2 = (opcode == 7'b0010011) ? imm_ext : rs2_in;
                    aluop = 8'd6;
                    out = rd_output;
                end

                endcase
            end
        end
        
        7'b0110111,7'b0010111 : begin //U-TYPE 
            wr_en_rf = 1;

            aluop = 0;
            out = (opcode == 7'b0110111) ? imm_ext : pc + imm_ext;
        end

        7'b1100011 : begin //B-TYPE
            
            case(funct3)
            
            3'b000 : begin //BEQ
                alu_in1 = rs1_in;
                alu_in2 = rs2_in;
                aluop = 8'd2;
                jump_pc = pc + imm_ext;
                is_jump = (rs1_in == rs2_in);           
            end

            3'b001 : begin //BNE
                alu_in1 = rs1_in;
                alu_in2 = rs2_in;
                aluop = 8'd2;
                jump_pc = pc + imm_ext;
                is_jump = (rs1_in != rs2_in);           
            end

            endcase
        end

        7'b1101111 : begin //J-TYPE
            wr_en_rf = 1; //JAL
            is_jump = 1;
            jump_pc = pc + imm_ext;
            out = pc + 4;
        end

        7'b0100011 : begin //S-TYPE
            wr_en_mem = 1;
            
            alu_in1 = rs1_in;
            alu_in2 = imm_ext;
            aluop = 8'd1;
            mem_data_wr = rs2_in;
            mem_addr = rd_output[31:0];

            case(funct3)

            3'b000 : begin //SB
                case(byte_sel)

                2'b00 : mem_mask = 4'b0001;
                2'b01 : mem_mask = 4'b0010;
                2'b10 : mem_mask = 4'b0100;
                2'b11 : mem_mask = 4'b1000;

                endcase
            end 

            3'b001 : mem_mask = (byte_sel[1]) ? 4'b1100 : 4'b0011; //SH

            3'b010 : mem_mask = 4'b1111; ///SW

            endcase
        end

        7'b0000011 : begin //LOAD
            wr_en_rf = 1;
            read_en_mem = 1;
            alu_in1 = rs1_in;
            alu_in2 = imm_ext;
            aluop = 8'd1;
            mem_addr = rd_output[31:0];
            mem_mask = 4'b1111;
            out = mem_read;
        end

        default : begin
            wr_en_rf = 0;
            wr_en_mem = 0;
            is_jump =  0;
            aluop = 8'd0;
        end

        endcase

    end

    
endmodule

rtl/alu.v
module ALU (
    input [7:0] alucode,
    input [31:0] rs1,
    input [31:0] rs2,
    output reg [63:0] rd
);


    always @(*) begin
    
        case(alucode)

        8'd1 : rd = rs1 + rs2 ; //ADD
        8'd2 : rd = rs1 - rs2 ; //SUB
        8'd3 : rd = rs1 * rs2 ; //MUL
        8'd4 : rd = (rs2 == 0) ? -1 : $signed(rs1) / $signed(rs2) ; //DIV
        8'd5 : rd = (rs2 == 0) ? rs1 : $signed(rs1) % $signed(rs2) ; //REM
        8'd6 : rd = rs1 & rs2 ; //AND
        8'd7 : rd = rs1 | rs2 ; //OR
        8'd8 : rd = rs1 ^ rs2 ; //XOR
        8'd9 : rd = rs1 << rs2[4:0] ; //SLL
        8'd10 : rd = rs1 >> rs2[4:0] ; //SRL
        8'd11 : rd = $signed(rs1) >>> rs2[4:0] ; //SRA
        8'd12 : rd = (rs2 == 0) ? -1 : rs1 / rs2 ; //DIVU
        8'd13 : rd = (rs2 == 0)  ? rs1 : rs1 % rs2 ;  //REMU
        8'd14 : rd = ($signed(rs1) < $signed(rs2)) ? 64'd1 : 64'd0 ; //SLT
        8'd15 : rd = (rs1 < rs2) ? 64'd1 : 64'd0 ; //SLTU
        8'd16 : rd = $signed(rs1) * $signed(rs2) ; //MULH
        8'd17 : rd = $signed(rs1) * $signed({1'b0, rs2}) ; //MULHSU
        default : rd = 0 ; //DEFAULT

        endcase

    end
  
endmodule

rtl/decoder.v
module DECODER (
    input [31:0] instr,
    output [4:0] rs1_addr,
    output [4:0] rs2_addr,
    output [4:0] rd_addr,
    output [6:0] opcode,
    output [2:0] funct3,
    output [6:0] funct7,
    output [31:0] imm_ext;
);

    wire is_i_instr;
    wire is_u_instr;
    wire is_b_instr;
    wire is_j_instr;
    wire is_s_instr;
    wire is_m_instr;

    assign opcode = instr[6:0];
    assign rd_addr = instr[11:7];
    assign funct3 = instr[14:12];
    assign rs1_addr = instr[19:15];
    assign rs2_addr = instr[24:20];
    assign funct7 = instr[31:25];

    always @(*) begin
        
        if ((opcode == 7'b0010011) || (opcode == 7'b0000011)) begin 
            imm_ext = {{20{instr[31]}}, instr[31:20]} ; end //I-Type Instruction
        else if ((opcode == 7'b0110111) || (opcode == 7'b0010111)) begin 
             imm_ext = {instr[31:12], 12'b0} ; end //U-Type Instruction
        else if ((opcode == 7'b1100011)) begin 
             imm_ext = {{19{instr[31]}}, instr[31], instr[7], instr[30:25], instr[11:8], 1'b0} ; end //B-Type Instruction 
        else if ((opcode == 7'b1101111)) begin 
             imm_ext = {{11{instr[31]}}, instr[31], instr[19:12], instr[20], instr[30:21], 1'b0} ; end //J-Type Instruction
        else if ((opcode == 7'b0100011);) begin 
            imm_ext = {{20{instr[31]}}, instr[31:25], instr[11:7]} ; end //S-Type Instruction
        else begin
            imm_ext = 32'b0; end

    end
  
endmodule

rtl/datamem.v
module DATAMEM (
    input clk,
    input [31:0] addr,
    input [31:0] mem_data_wr,
    input wr_en_mem,
    input read_en_mem,
    input [3:0] mem_mask,
    output reg [31:0] mem_read_data
);

    reg [31:0] datamem [0:2047];
    wire [10:0] word_addr = addr[12:2];

    initial begin
    $readmemh("./sim/data_mem.hex", datamem);
    end

    always @(*) begin

        if(read_en_mem) begin

            case(mem_mask)

            4'b0001 : mem_read_data = {{24{datamem[word_addr][7]}}, datamem[word_addr][7:0] };
            4'b0010 : mem_read_data = {{24{datamem[word_addr][15]}}, datamem[word_addr][15:8] };
            4'b0100 : mem_read_data = {{24{datamem[word_addr][23]}}, datamem[word_addr][23:16] };
            4'b1000 : mem_read_data = {{24{datamem[word_addr][31]}}, datamem[word_addr][31:24] };
            4'b0011 : mem_read_data = {{16{datamem[word_addr][15]}}, datamem[word_addr][15:0] };
            4'b1100 : mem_read_data = {{16{datamem[word_addr][31]}}, datamem[word_addr][31:16] };
            4'b1111 : mem_read_data = datamem[word_addr];
            default : mem_read_data = datamem[word_addr];

            endcase

        end
        else begin 
            mem_read_data = 32'b0;
        end
    end

    always @(posedge clk) begin
        
        if(wr_en_mem) begin

            if(mem_mask[0]) datamem[word_addr][7:0] <= mem_data_wr[7:0];
            if(mem_mask[1]) datamem[word_addr][15:8] <= mem_data_wr[15:8];
            if(mem_mask[2]) datamem[word_addr][23:16] <= mem_data_wr[23:16];
            if(mem_mask[3]) datamem[word_addr][31:24] <= mem_data_wr[31:24];

        end

    end

endmodule

rtl/instrmem.v
module INSTRMEM (
    input [31:0] instr_addr,
    output [31:0] instr
);

reg [31:0] instrmem [0:511];

initial begin
$readmemh("C:\Users\Mayuresh\OneDrive\Desktop\Sanganac\Sanganac\sim\instr_program.hex", instrmem)
end

assign instr = instrmem[instr_addr >> 2];
    
endmodule

rtl/regfile.v
module REGFILE (
    input clk,
    input wr_en,
    input [4:0] rs1_addr,
    input [4:0] rs2_addr,
    input [4:0] rd_addr,
    input [31:0] rd,
    output wire [31:0] rs1,
    output wire [31:0] rs2
);


    reg [31:0] regfile [31:0];

    initial begin
        
        regfile[0] <= 0;
        regfile[1] <= 0;
        regfile[2] <= 0;
        regfile[3] <= 0;
        regfile[4] <= 0;
        regfile[5] <= 0;
        regfile[6] <= 0;
        regfile[7] <= 0;
        regfile[8] <= 0;
        regfile[9] <= 0;
        regfile[10] <= 0;
        regfile[11] <= 0;
        regfile[12] <= 0;
        regfile[13] <= 0;
        regfile[14] <= 0;
        regfile[15] <= 0;
        regfile[16] <= 0;
        regfile[17] <= 0;
        regfile[18] <= 0;
        regfile[19] <= 0;
        regfile[20] <= 0;
        regfile[21] <= 0;
        regfile[22] <= 0;
        regfile[23] <= 0;
        regfile[24] <= 0;
        regfile[25] <= 0;
        regfile[26] <= 0;
        regfile[27] <= 0;
        regfile[28] <= 0;
        regfile[29] <= 0;
        regfile[30] <= 0;
        regfile[31] <= 0;

    end

    always @(*) begin
        rs1 = regfile[rs1_addr];
        rs2 = regfile[rs2_addr];   
    end

    always @(posedge clk) begin
        regfile[0] <= 0;

        if (wr_en && rd_addr != 5'd0) begin
            regfile[rd_addr] <= rd;
        end
    end


endmodule

rtl/pc.v
module PC (
    input clk,
    input reset,
    input [31:0] jump_pc,
    input is_jump,
    output [31:0] pc_next
);

    reg [31:0] pc;

    always @(posedge clk or posedge reset) begin
        
        if (reset) begin
            pc <= 32'b0;
        end
        else if (is_jump) begin
            pc <= jump_pc;
        end
        else begin
            pc <= pc + 32'd4;
        end
    
    end

    assign pc_next = pc;
    
endmodule

rtl/riscv_core.v
module RISCV_CORE (
    input clk,
    input reset
);

    wire [31:0] pc_current, jump_pc, instr, imm_ext;
    wire [4:0] rs1_addr, rs2_addr, rd_addr;
    wire [31:0] rs1, rs2, rd;
    wire [63:0] alu_output;
    wire [31:0] alu_in1, alu_in2;
    wire [31:0] mem_addr, mem_read_data, mem_data_wr;
    wire [6:0] opcode, funct7;
    wire [2:0] funct3;
    wire [7:0] aluop;
    wire [3:0] mem_mask;
    wire wr_en_rf, wr_en_mem, read_en_mem, is_jump;

    PC pc (
        .clk(clk),
        .reset(reset),
        .jump_pc(jump_pc),
        .is_jump(is_jump),
        .pc_next(pc_current)
    );

    REGFILE regfile (
        .clk(clk),
        .wr_en(wr_en_rf),
        .rs1_addr(rs1_addr),
        .rs2_addr(rs2_addr),
        .rd_addr(rd_addr),
        .rd(rd),
        .rs1(rs1),
        .rs2(rs2)
    );

    INSTRMEM instrmem (
        .instr_addr(pc_current),
        .instr(instr)
    );

    DATAMEM datamem (
        .clk(clk),
        .addr(mem_addr),
        .mem_data_wr(mem_data_wr),
        .wr_en_mem(wr_en_mem),
        .read_en_mem(read_en_mem),
        .mem_mask(mem_mask),
        .mem_read_data(mem_read_data)
);  

    DECODER decoder (
        .instr(instr),
        .rs1_addr(rs1_addr),
        .rs2_addr(rs2_addr),
        .rd_addr(rd_addr),
        .opcode(opcode),
        .funct3(funct3),
        .funct7(funct7),
        .imm_ext(imm_ext)
    );

    ALU alu (
        .alucode(aluop),
        .rs1(alu_in1),
        .rs2(alu_in2),
        .rd(alu_output)
    );

    CONTROL_UNIT control_unit (
        .clk(clk),
        .reset(reset),

        .pc(pc_current),
        .mem_read(mem_read_data),
        .rs1_in(rs1),
        .rs2_in(rs2),
        .rd_output(alu_output),
        .opcode(opcode),
        .funct3(funct3),
        .funct7(funct7),
        .imm_ext(imm_ext),

        .alu_in1(alu_in1),
        .alu_in2(alu_in2),
        .out(rd), 
        .aluop(aluop),
        .wr_en_rf(wr_en_rf),
        .wr_en_mem(wr_en_mem),
        .read_en_mem(read_en_mem),
        .mem_data_wr(mem_data_wr),
        .mem_addr(mem_addr),
        .mem_mask(mem_mask),
        .jump_pc(jump_pc),
        .is_jump(is_jump)
    );
    
endmodule

rtl/top.v
module TOP (
    input clk,
    input reset
);

    RISCV_CORE sanganac (
        .clk(clk),
        .reset(reset)
    );

endmodule

tb/tb.v
`timescale 1ns/1ps

module tb ();
    
    reg clk;
    reg reset;
    integer i;

    TOP uut (
        .clk(clk),
        .reset(reset)
    );

    initial begin
        clk = 0;
        forever #5 clk = ~clk; 
    end

    initial begin
        $dumpfile("tb.vcd");
        $dumpvars(0, tb);
    end

    initial begin
        reset = 1;
        #50 reset = 0;
        
        #500;

        // ABCDE537  00: LUI X10, 0XABCDE      X10 = 0XABCDE000
        // 00A00093   04: ADDI X1, X0, 10       X1 = 10
        // 00300113   08: ADDI X2, X0, 3        X2 = 3
        // 002081B3   0C: ADD X3, X1, X2        X3 = 13
        // 40208233   10: SUB X4, X1, X2        X4 = 7
        // 022082B3   14: MUL X5, X1, X2        X5 = 30
        // 0220D333   18: DIV X6, X1, X2        X6 = 3
        // 0220F3B3   1C: REM X7, X1, X2        X7 = 1
        // 0023D433   20: SRL X8, X7, X2        X8 = 1 >> 3 = 0
        // 00552023   24: SW  X5, 0X10          STORE X5 (30) AT DATA MEMORY ADDRESS 0
        // 00052483   28: LW  X9, 0X10          LOAD FROM DATA MEMORY ADDRESS 0 INTO X9
        // 00928663   2C: BEQ X5, X9, 12        IF 30 == 30, JUMP +12 BYTES TO PC 38
        // 00100513   30: ADDI X10, X0, 1       TRAP: SHOULD BE SKIPPED
        // 00100513   34: ADDI X10, X0, 1       TRAP: SHOULD BE SKIPPED
        // 01E00613  38: ADDI X12, X0, 30      SUCCESS: X12 = 30
        // 0000006F   3C: JAL X0, 0             INFINITE LOOP

        $display("Simulation now completed.");

        $display("======================================================");
        $display("REGISTER FILE :"); 
        for (i = 0; i < 32; i = i + 1) begin
            $display("x%0d : %h", i, uut.sanganac.regfile.regfile[i]);
        end
        $display("======================================================");

        $display("");
        $display("======================================================");
        $display("INSTRUCTION MEMORY :");
        for (i = 0; i < 20; i = i + 1) begin
            $display("%h : %h", i*4, uut.sanganac.instrmem.instrmem[i]);
        end
        $display("======================================================");

        $display("");
        $display("======================================================");
        $display("DATA MEMORY :");
        for (i = 0; i < 20; i = i + 1) begin
            $display("%h : %h", i*4, uut.sanganac.datamem.datamem[i]);
        end
        $display("======================================================");

        $display("");

        $finish;

    end

    initial begin
        $monitor("Time : %0t | Reset : %b | PC : %h | Instruction : %h", 
                 $time, reset, uut.sanganac.pc_current, uut.sanganac.instr);
    end

endmodule

sim/tb.vcd
$date
	Sat Jan 24 21:21:34 2026
$end
$version
	Icarus Verilog
$end
$timescale
	1ps
$end
$scope module tb $end
$var reg 1 ! clk $end
$var reg 1 " reset $end
$var integer 32 # i [31:0] $end
$scope module uut $end
$var wire 1 ! clk $end
$var wire 1 " reset $end
$scope module sanganac $end
$var wire 1 ! clk $end
$var wire 1 " reset $end
$var wire 1 $ wr_en_rf $end
$var wire 1 % wr_en_mem $end
$var wire 5 & rs2_addr [4:0] $end
$var wire 32 ' rs2 [31:0] $end
$var wire 5 ( rs1_addr [4:0] $end
$var wire 32 ) rs1 [31:0] $end
$var wire 1 * read_en_mem $end
$var wire 5 + rd_addr [4:0] $end
$var wire 32 , rd [31:0] $end
$var wire 32 - pc_current [31:0] $end
$var wire 7 . opcode [6:0] $end
$var wire 32 / mem_read_data [31:0] $end
$var wire 4 0 mem_mask [3:0] $end
$var wire 32 1 mem_data_wr [31:0] $end
$var wire 32 2 mem_addr [31:0] $end
$var wire 32 3 jump_pc [31:0] $end
$var wire 1 4 is_jump $end
$var wire 32 5 instr [31:0] $end
$var wire 32 6 imm_ext [31:0] $end
$var wire 7 7 funct7 [6:0] $end
$var wire 3 8 funct3 [2:0] $end
$var wire 8 9 aluop [7:0] $end
$var wire 64 : alu_output [63:0] $end
$var wire 32 ; alu_in2 [31:0] $end
$var wire 32 < alu_in1 [31:0] $end
$scope module alu $end
$var wire 32 = rs2 [31:0] $end
$var wire 32 > rs1 [31:0] $end
$var wire 8 ? alucode [7:0] $end
$var reg 64 @ rd [63:0] $end
$upscope $end
$scope module control_unit $end
$var wire 1 ! clk $end
$var wire 64 A rd_output [63:0] $end
$var wire 1 " reset $end
$var wire 32 B rs2_in [31:0] $end
$var wire 32 C rs1_in [31:0] $end
$var wire 32 D pc [31:0] $end
$var wire 7 E opcode [6:0] $end
$var wire 32 F mem_read [31:0] $end
$var wire 32 G imm_ext [31:0] $end
$var wire 7 H funct7 [6:0] $end
$var wire 3 I funct3 [2:0] $end
$var wire 2 J byte_sel [1:0] $end
$var reg 32 K alu_in1 [31:0] $end
$var reg 32 L alu_in2 [31:0] $end
$var reg 8 M aluop [7:0] $end
$var reg 1 4 is_jump $end
$var reg 32 N jump_pc [31:0] $end
$var reg 32 O mem_addr [31:0] $end
$var reg 32 P mem_data_wr [31:0] $end
$var reg 4 Q mem_mask [3:0] $end
$var reg 32 R out [31:0] $end
$var reg 1 * read_en_mem $end
$var reg 1 % wr_en_mem $end
$var reg 1 $ wr_en_rf $end
$upscope $end
$scope module datamem $end
$var wire 32 S addr [31:0] $end
$var wire 1 ! clk $end
$var wire 32 T mem_data_wr [31:0] $end
$var wire 4 U mem_mask [3:0] $end
$var wire 1 * read_en_mem $end
$var wire 1 % wr_en_mem $end
$var wire 11 V word_addr [10:0] $end
$var reg 32 W mem_read_data [31:0] $end
$upscope $end
$scope module decoder $end
$var wire 5 X rs2_addr [4:0] $end
$var wire 5 Y rs1_addr [4:0] $end
$var wire 5 Z rd_addr [4:0] $end
$var wire 7 [ opcode [6:0] $end
$var wire 32 \ instr [31:0] $end
$var wire 7 ] funct7 [6:0] $end
$var wire 3 ^ funct3 [2:0] $end
$var reg 32 _ imm_ext [31:0] $end
$upscope $end
$scope module instrmem $end
$var wire 32 ` instr [31:0] $end
$var wire 32 a instr_addr [31:0] $end
$upscope $end
$scope module pc $end
$var wire 1 ! clk $end
$var wire 1 4 is_jump $end
$var wire 32 b jump_pc [31:0] $end
$var wire 32 c pc_next [31:0] $end
$var wire 1 " reset $end
$var reg 32 d pc [31:0] $end
$upscope $end
$scope module regfile $end
$var wire 1 ! clk $end
$var wire 32 e rd [31:0] $end
$var wire 5 f rd_addr [4:0] $end
$var wire 5 g rs1_addr [4:0] $end
$var wire 5 h rs2_addr [4:0] $end
$var wire 1 $ wr_en $end
$var wire 32 i rs2 [31:0] $end
$var wire 32 j rs1 [31:0] $end
$upscope $end
$upscope $end
$upscope $end
$upscope $end
$enddefinitions $end
#0
$dumpvars
b0 j
b0 i
b11100 h
b11011 g
b1010 f
b10101011110011011110000000000000 e
b0 d
b0 c
b10101011110011011110000000000000 b
b0 a
b10101011110011011110010100110111 `
b10101011110011011110000000000000 _
b110 ^
b1010101 ]
b10101011110011011110010100110111 \
b110111 [
b1010 Z
b11011 Y
b11100 X
b0 W
b0 V
b0 U
b0 T
b0 S
b10101011110011011110000000000000 R
b0 Q
b0 P
b0 O
b10101011110011011110000000000000 N
b0 M
b0 L
b0 K
b0 J
b110 I
b1010101 H
b10101011110011011110000000000000 G
b0 F
b110111 E
b0 D
b0 C
b0 B
b0 A
b0 @
b0 ?
b0 >
b0 =
b0 <
b0 ;
b0 :
b0 9
b110 8
b1010101 7
b10101011110011011110000000000000 6
b10101011110011011110010100110111 5
04
b10101011110011011110000000000000 3
b0 2
b0 1
b0 0
b0 /
b110111 .
b0 -
b10101011110011011110000000000000 ,
b1010 +
0*
b0 )
b11011 (
b0 '
b11100 &
0%
1$
bx #
1"
0!
$end
#5000
1!
#10000
0!
#15000
1!
#20000
0!
#25000
1!
#30000
0!
#35000
1!
#40000
0!
#45000
1!
#50000
0!
0"
#55000
b10 V
b10 J
b1010 2
b1010 O
b1010 S
b10101011110011011110000000000000 1
b10101011110011011110000000000000 P
b10101011110011011110000000000000 T
b1010 :
b1010 @
b1010 A
b10101011110011011110000000000000 '
b10101011110011011110000000000000 B
b10101011110011011110000000000000 i
b1 9
b1 ?
b1 M
b1010 ;
b1010 =
b1010 L
b0 7
b0 H
b0 ]
b1010 &
b1010 X
b1010 h
b0 (
b0 Y
b0 g
b0 8
b0 I
b0 ^
b1 +
b1 Z
b1 f
b10011 .
b10011 E
b10011 [
b1010 6
b1010 G
b1010 _
b101000000000000010010011 5
b101000000000000010010011 \
b101000000000000010010011 `
b1110 3
b1110 N
b1110 b
1$
b1010 ,
b1010 R
b1010 e
b100 -
b100 D
b100 a
b100 c
b100 d
1!
#60000
0!
#65000
b0 V
b11 J
b11 2
b11 O
b11 S
b0 1
b0 P
b0 T
b11 :
b11 @
b11 A
b0 '
b0 B
b0 i
b11 &
b11 X
b11 h
b10 +
b10 Z
b10 f
b11 6
b11 G
b11 _
b1100000000000100010011 5
b1100000000000100010011 \
b1100000000000100010011 `
b1011 3
b1011 N
b1011 b
1$
b1 9
b1 ?
b1 M
b11 ,
b11 R
b11 e
b11 ;
b11 =
b11 L
b1000 -
b1000 D
b1000 a
b1000 c
b1000 d
1!
#70000
0!
#75000
b11 V
b1 J
b1101 2
b1101 O
b1101 S
b11 1
b11 P
b11 T
b1010 <
b1010 >
b1010 K
b1101 :
b1101 @
b1101 A
b11 '
b11 B
b11 i
b1010 )
b1010 C
b1010 j
b10 &
b10 X
b10 h
b1 (
b1 Y
b1 g
b11 +
b11 Z
b11 f
b110011 .
b110011 E
b110011 [
b0 6
b0 G
b0 _
b1000001000000110110011 5
b1000001000000110110011 \
b1000001000000110110011 `
b1100 3
b1100 N
b1100 b
1$
b1 9
b1 ?
b1 M
b1101 ,
b1101 R
b1101 e
b11 ;
b11 =
b11 L
b1100 -
b1100 D
b1100 a
b1100 c
b1100 d
1!
#80000
0!
#85000
b1 V
b111 2
b111 O
b111 S
b11 J
b111 :
b111 @
b111 A
b100000 7
b100000 H
b100000 ]
b100 +
b100 Z
b100 f
b1000000001000001000001000110011 5
b1000000001000001000001000110011 \
b1000000001000001000001000110011 `
b10000 3
b10000 N
b10000 b
1$
b10 9
b10 ?
b10 M
b111 ,
b111 R
b111 e
b10000 -
b10000 D
b10000 a
b10000 c
b10000 d
1!
#90000
0!
#95000
b111 V
b11110 2
b11110 O
b11110 S
b10 J
b11110 :
b11110 @
b11110 A
b1 7
b1 H
b1 ]
b101 +
b101 Z
b101 f
b10001000001000001010110011 5
b10001000001000001010110011 \
b10001000001000001010110011 `
b10100 3
b10100 N
b10100 b
1$
b11 9
b11 ?
b11 M
b11110 ,
b11110 R
b11110 e
b10100 -
b10100 D
b10100 a
b10100 c
b10100 d
1!
#100000
0!
#105000
b0 V
b11 2
b11 O
b11 S
b11 J
b11 :
b11 @
b11 A
b101 8
b101 I
b101 ^
b110 +
b110 Z
b110 f
b10001000001101001100110011 5
b10001000001101001100110011 \
b10001000001101001100110011 `
b11000 3
b11000 N
b11000 b
1$
b100 9
b100 ?
b100 M
b11 ,
b11 R
b11 e
b11000 -
b11000 D
b11000 a
b11000 c
b11000 d
1!
#110000
0!
#115000
b1 2
b1 O
b1 S
b1 J
b1 :
b1 @
b1 A
b111 8
b111 I
b111 ^
b111 +
b111 Z
b111 f
b10001000001111001110110011 5
b10001000001111001110110011 \
b10001000001111001110110011 `
b11100 3
b11100 N
b11100 b
1$
b101 9
b101 ?
b101 M
b1 ,
b1 R
b1 e
b11100 -
b11100 D
b11100 a
b11100 c
b11100 d
1!
#120000
0!
#125000
b0 2
b0 O
b0 S
b0 J
b0 :
b0 @
b0 A
b1 <
b1 >
b1 K
b1 )
b1 C
b1 j
b0 7
b0 H
b0 ]
b111 (
b111 Y
b111 g
b101 8
b101 I
b101 ^
b1000 +
b1000 Z
b1000 f
b1000111101010000110011 5
b1000111101010000110011 \
b1000111101010000110011 `
b100000 3
b100000 N
b100000 b
1$
b1010 9
b1010 ?
b1010 M
b0 ,
b0 R
b0 e
b100000 -
b100000 D
b100000 a
b100000 c
b100000 d
1!
#130000
0!
#135000
b0 J
b10101011110011011110000000000000 2
b10101011110011011110000000000000 O
b10101011110011011110000000000000 S
b11110 1
b11110 P
b11110 T
b10101011110011011110000000000000 <
b10101011110011011110000000000000 >
b10101011110011011110000000000000 K
b10101011110011011110000000000000 :
b10101011110011011110000000000000 @
b10101011110011011110000000000000 A
b11110 '
b11110 B
b11110 i
b10101011110011011110000000000000 )
b10101011110011011110000000000000 C
b10101011110011011110000000000000 j
b1111 0
b1111 Q
b1111 U
b0 ;
b0 =
b0 L
1%
b101 &
b101 X
b101 h
b1010 (
b1010 Y
b1010 g
b10 8
b10 I
b10 ^
b0 +
b0 Z
b0 f
b100011 .
b100011 E
b100011 [
b10101010010000000100011 5
b10101010010000000100011 \
b10101010010000000100011 `
b100100 3
b100100 N
b100100 b
0$
b1 9
b1 ?
b1 M
b100100 -
b100100 D
b100100 a
b100100 c
b100100 d
1!
#140000
0!
#145000
b0 V
b0 J
b11110 ,
b11110 R
b11110 e
b10101011110011011110000000000000 2
b10101011110011011110000000000000 O
b10101011110011011110000000000000 S
b0 1
b0 P
b0 T
b11110 /
b11110 F
b11110 W
b10101011110011011110000000000000 :
b10101011110011011110000000000000 @
b10101011110011011110000000000000 A
b0 '
b0 B
b0 i
1*
1$
b0 &
b0 X
b0 h
b1001 +
b1001 Z
b1001 f
b11 .
b11 E
b11 [
b0 6
b0 G
b0 _
b1010010010010000011 5
b1010010010010000011 \
b1010010010010000011 `
b101000 3
b101000 N
b101000 b
b1111 0
b1111 Q
b1111 U
0%
b1 9
b1 ?
b1 M
b0 ;
b0 =
b0 L
b101000 -
b101000 D
b101000 a
b101000 c
b101000 d
1!
#150000
0!
#155000
b0 2
b0 O
b0 S
b0 :
b0 @
b0 A
14
b11110 1
b11110 P
b11110 T
b11110 ;
b11110 =
b11110 L
b11110 <
b11110 >
b11110 K
b0 /
b0 F
b0 W
b11110 '
b11110 B
b11110 i
b11110 )
b11110 C
b11110 j
b1001 &
b1001 X
b1001 h
b101 (
b101 Y
b101 g
b0 8
b0 I
b0 ^
b1100 +
b1100 Z
b1100 f
b1100011 .
b1100011 E
b1100011 [
b1100 6
b1100 G
b1100 _
b100100101000011001100011 5
b100100101000011001100011 \
b100100101000011001100011 `
b111000 3
b111000 N
b111000 b
b0 0
b0 Q
b0 U
0*
0$
b10 9
b10 ?
b10 M
b0 ,
b0 R
b0 e
b101100 -
b101100 D
b101100 a
b101100 c
b101100 d
1!
#160000
0!
#165000
b10 J
b111 V
b11110 ,
b11110 R
b11110 e
b11110 2
b11110 O
b11110 S
b0 1
b0 P
b0 T
b11110 ;
b11110 =
b11110 L
b0 <
b0 >
b0 K
b11110 :
b11110 @
b11110 A
b0 '
b0 B
b0 i
b0 )
b0 C
b0 j
1$
b11110 6
b11110 G
b11110 _
b11110 &
b11110 X
b11110 h
b0 (
b0 Y
b0 g
b10011 .
b10011 E
b10011 [
b1111000000000011000010011 5
b1111000000000011000010011 \
b1111000000000011000010011 `
04
b1010110 3
b1010110 N
b1010110 b
b1 9
b1 ?
b1 M
b111000 -
b111000 D
b111000 a
b111000 c
b111000 d
1!
#170000
0!
#175000
b0 V
b0 2
b0 O
b0 S
b0 J
b0 :
b0 @
b0 A
14
b0 &
b0 X
b0 h
b0 +
b0 Z
b0 f
b1101111 .
b1101111 E
b1101111 [
b0 6
b0 G
b0 _
b1101111 5
b1101111 \
b1101111 `
b111100 3
b111100 N
b111100 b
1$
b0 9
b0 ?
b0 M
b1000000 ,
b1000000 R
b1000000 e
b0 ;
b0 =
b0 L
b111100 -
b111100 D
b111100 a
b111100 c
b111100 d
1!
